[{"line":3,"elements":[{"line":4,"name":"","description":"","type":"background","keyword":"Background","steps":[{"result":{"duration":24207000,"status":"passed"},"line":5,"name":"user in TalentTEK Homepage","match":{"location":"stepDef.LoginSteps.userInTalentTEKHomepage()"},"keyword":"Given "}]},{"start_timestamp":"2023-03-21T01:11:49.848Z","before":[{"result":{"duration":9330234000,"status":"passed"},"match":{"location":"stepDef.Hook.beforeEachTest()"}}],"line":8,"name":"User should be able to login with valid email and password","description":"","id":"login-feature;user-should-be-able-to-login-with-valid-email-and-password","after":[{"result":{"duration":790000,"status":"passed"},"match":{"location":"stepDef.Hook.afterEachTest(io.cucumber.java.Scenario)"}}],"type":"scenario","keyword":"Scenario","steps":[{"result":{"duration":261784000,"status":"passed"},"line":9,"name":"user enter valid email address","match":{"location":"stepDef.LoginSteps.userEnterValidEmailAddress()"},"keyword":"And "},{"result":{"duration":66748000,"status":"passed"},"line":10,"name":"user enter valid password","match":{"location":"stepDef.LoginSteps.userEnterValidPassword()"},"keyword":"And "},{"result":{"duration":255571000,"status":"passed"},"line":11,"name":"user clicks on Log In button","match":{"location":"stepDef.LoginSteps.userClicksOnLogInButton()"},"keyword":"When "},{"result":{"duration":479887000,"status":"passed"},"line":12,"name":"user should be able to successfully login","match":{"location":"stepDef.LoginSteps.userShouldBeAbleToSuccessfullyLogin()"},"keyword":"Then "}],"tags":[{"name":"@regression"},{"name":"@smoke"},{"name":"@sanity"},{"name":"@test"}]}],"name":"Login Feature","description":"","id":"login-feature","keyword":"Feature","uri":"file:src/test/java/features/login.feature","tags":[]},{"line":1,"elements":[{"start_timestamp":"2023-03-21T01:12:00.289Z","before":[{"result":{"duration":6113717000,"status":"passed"},"match":{"location":"stepDef.Hook.beforeEachTest()"}}],"line":4,"name":"User should be able to create a brand new email with unique email address","description":"","id":"signup-feature;user-should-be-able-to-create-a-brand-new-email-with-unique-email-address","after":[{"result":{"duration":31000,"status":"passed"},"match":{"location":"stepDef.Hook.afterEachTest(io.cucumber.java.Scenario)"}}],"type":"scenario","keyword":"Scenario","steps":[{"result":{"duration":16670000,"status":"passed"},"line":5,"name":"user in TalentTEK Homepage","match":{"location":"stepDef.LoginSteps.userInTalentTEKHomepage()"},"keyword":"Given "},{"result":{"duration":483110000,"status":"passed"},"line":6,"name":"user click on \"Create new account\" button","match":{"arguments":[{"val":"\"Create new account\"","offset":14}],"location":"stepDef.LoginSteps.userClickOnButton(java.lang.String)"},"keyword":"And "},{"result":{"duration":321512000,"status":"passed"},"line":7,"name":"user enter First and Last Name","match":{"location":"stepDef.SignupSteps.userEnterFirstAndLastName()"},"keyword":"And "},{"result":{"duration":65562000,"status":"passed"},"line":8,"name":"user enter their valid email address","match":{"location":"stepDef.SignupSteps.userEnterTheirValidEmailAddress()"},"keyword":"And "},{"result":{"duration":106752000,"status":"passed"},"line":11,"name":"user enter \"Oct\" under Birth Date","match":{"arguments":[{"val":"\"Oct\"","offset":11}],"location":"stepDef.SignupSteps.userEnterUnderBirthDate(java.lang.String)"},"keyword":"And "},{"result":{"status":"undefined"},"line":14,"name":"user enter their gender as \"female\"","match":{},"keyword":"And "}],"tags":[{"name":"@regression"},{"name":"@smoke"},{"name":"@sanity"},{"name":"@test"}]}],"name":"Signup Feature","description":"","id":"signup-feature","keyword":"Feature","uri":"file:src/test/java/features/signup.feature","tags":[]}]